datatotable/__init__.py
datatotable/data.py
datatotable/database.py
datatotable/typecheck.py
datatotable-0.3.1.dist-info/LICENSE
datatotable-0.3.1.dist-info/METADATA
datatotable-0.3.1.dist-info/WHEEL
datatotable-0.3.1.dist-info/top_level.txt
datatotable-0.3.1.dist-info/RECORD
