Metadata-Version: 2.1
Name: datatotable
Version: 0.3.1
Summary: Create SQLite database tables automatically from data
Home-page: https://github.com/Spencer-Weston/DatatoTable
Author: Spencer Weston
Author-email: Spencerweston3214@gmail.com
License: MIT
Keywords: data SQL sql SQLalchemy web-scraping data-management
Platform: UNKNOWN
Classifier: License :: OSI Approved :: MIT License
Requires-Dist: SQLAlchemy (>=1.2.17)
